{"name_to_sgg_code": {"서울특별시|종로구": "G6_000", "서울특별시|중구": "G6_001", "서울특별시|동대문구 갑": "G6_002", "서울특별시|동대문구 을": "G6_003", "서울특별시|성동구 갑": "G6_004", "서울특별시|성동구 을": "G6_005", "서울특별시|성북구 갑": "G6_006", "서울특별시|성북구 을": "G6_007", "서울특별시|서대문구 갑": "G6_008", "서울특별시|서대문구 을": "G6_009", "서울특별시|마포구": "G6_010", "서울특별시|용산구": "G6_011", "서울특별시|영등포구 갑": "G6_012", "서울특별시|영등포구 을": "G6_013", "부산광역시|중구": "G6_014", "부산광역시|영도구": "G6_015", "부산광역시|서구": "G6_016", "부산광역시|동구": "G6_017", "부산광역시|부산진구 갑": "G6_018", "부산광역시|부산진구 을": "G6_019", "부산광역시|동래구": "G6_020", "경기도|인천시 갑": "G6_021", "경기도|인천시 을": "G6_022", "경기도|수원시": "G6_023", "경기도|의정부시·양주군": "G6_024", "경기도|광주군·이천군": "G6_025", "경기도|포천군·가평군·연천군": "G6_026", "경기도|여주군·양평군": "G6_027", "경기도|용인군·안성군": "G6_028", "경기도|평택군": "G6_029", "경기도|화성군": "G6_030", "경기도|고양군·파주군": "G6_031", "경기도|김포군·강화군": "G6_032", "경기도|시흥군·부천군·옹진군": "G6_033", "강원특별자치도|춘천시·춘성군": "G6_034", "강원특별자치도|원주시·원성군": "G6_035", "강원특별자치도|강릉시·명주군": "G6_036", "강원특별자치도|홍천군·인제군": "G6_037", "강원특별자치도|영월군·정선군": "G6_038", "강원특별자치도|철원군·화천군·양구군": "G6_039", "강원특별자치도|속초시·양양군·고성군": "G6_040", "강원특별자치도|횡성군·평창군": "G6_041", "강원특별자치도|삼척군": "G6_042", "충청북도|청주시": "G6_043", "충청북도|청원군": "G6_044", "충청북도|충주시·중원군": "G6_045", "충청북도|옥천군·보은군": "G6_046", "충청북도|괴산군": "G6_047", "충청북도|영동군": "G6_048", "충청북도|진천군·음성군": "G6_049", "충청북도|제천군·단양군": "G6_050", "충청남도|대전시": "G6_051", "충청남도|대덕군·연기군": "G6_052", "충청남도|공주군": "G6_053", "충청남도|논산군": "G6_054", "충청남도|부여군": "G6_055", "충청남도|서천군·보령군": "G6_056", "충청남도|청양군·홍성군": "G6_057", "충청남도|예산군": "G6_058", "충청남도|서산군": "G6_059", "충청남도|당진군": "G6_060", "충청남도|아산군": "G6_061", "충청남도|천안시·천원군": "G6_062", "충청남도|금산군": "G6_063", "전북특별자치도|전주시": "G6_064", "전북특별자치도|군산시·옥구군": "G6_065", "전북특별자치도|이리시·익산군": "G6_066", "전북특별자치도|완주군": "G6_067", "전북특별자치도|진안군·장수군·무주군": "G6_068", "전북특별자치도|임실군·순창군": "G6_069", "전북특별자치도|남원군": "G6_070", "전북특별자치도|정읍군": "G6_071", "전북특별자치도|고창군": "G6_072", "전북특별자치도|부안군": "G6_073", "전북특별자치도|김제군": "G6_074", "전라남도|광주시 갑": "G6_075", "전라남도|광주시 을": "G6_076", "전라남도|목포시": "G6_077", "전라남도|여수시·여천군": "G6_078", "전라남도|순천시·승주군": "G6_079", "전라남도|담양군·장성군": "G6_080", "전라남도|화순군·곡성군": "G6_081", "전라남도|구례군·광양군": "G6_082", "전라남도|고흥군": "G6_083", "전라남도|보성군": "G6_084", "전라남도|장흥군": "G6_085", "전라남도|영암군·강진군": "G6_086", "전라남도|완도군": "G6_087", "전라남도|해남군": "G6_088", "전라남도|무안군": "G6_089", "전라남도|나주군": "G6_090", "전라남도|광산군": "G6_091", "전라남도|영광군·함평군": "G6_092", "전라남도|진도군": "G6_093", "경상북도|대구시 중구": "G6_094", "경상북도|대구시 동구": "G6_095", "경상북도|대구시 남구": "G6_096", "경상북도|대구시 북구·서구": "G6_097", "경상북도|포항시·영일군·울릉군": "G6_098", "경상북도|김천시·금릉군": "G6_099", "경상북도|경주시·월성군": "G6_100", "경상북도|달성군·고령군": "G6_101", "경상북도|군위군·선산군": "G6_102", "경상북도|의성군": "G6_103", "경상북도|안동시·안동군": "G6_104", "경상북도|청송군·영덕군": "G6_105", "경상북도|영양군·울진군": "G6_106", "경상북도|영천군": "G6_107", "경상북도|경산군·청도군": "G6_108", "경상북도|성주군·칠곡군": "G6_109", "경상북도|상주군": "G6_110", "경상북도|문경군": "G6_111", "경상북도|예천군": "G6_112", "경상북도|영주군·봉화군": "G6_113", "경상남도|마산시": "G6_114", "경상남도|진주시·진양군": "G6_115", "경상남도|충무시·통영군·고성군": "G6_116", "경상남도|거제군": "G6_117", "경상남도|진해시·창원군": "G6_118", "경상남도|삼천포시·사천군·하동군": "G6_119", "경상남도|함안군·의령군": "G6_120", "경상남도|창녕군": "G6_121", "경상남도|산청군·합천군": "G6_122", "경상남도|밀양군": "G6_123", "경상남도|양산군·동래군": "G6_124", "경상남도|울산시·울주군": "G6_125", "경상남도|김해군": "G6_126", "경상남도|남해군": "G6_127", "경상남도|함양군·거창군": "G6_128", "제주특별자치도|제주시·북제주군": "G6_129", "제주특별자치도|남제주군": "G6_130"}}