{
  "_meta": {
    "source": "nec-report-당선인명부",
    "is_final": true,
    "election_date": "1973-02-27",
    "fetched_at": "1973-02-27"
  },
  "races": [
    {
      "sg_typecode": "2",
      "scope": "district",
      "sido": "강원특별자치도",
      "sigungu": "제1선거구(춘천시·춘성군·화천군·양구군·철원군)",
      "district": "제1선거구(춘천시·춘성군·화천군·양구군·철원군)",
      "candidates": [
        {
          "name": "손승덕",
          "party": "민주공화당",
          "votes": 48626,
          "pct": 36.64,
          "rank": 1,
          "won": true
        },
        {
          "name": "홍창섭",
          "party": "무소속",
          "votes": 28740,
          "pct": 21.65,
          "rank": 2,
          "won": true
        }
      ]
    },
    {
      "sg_typecode": "2",
      "scope": "district",
      "sido": "강원특별자치도",
      "sigungu": "제2선거구(원주시·홍천군·횡성군·원성군)",
      "district": "제2선거구(원주시·홍천군·횡성군·원성군)",
      "candidates": [
        {
          "name": "박영록",
          "party": "신민당",
          "votes": 87978,
          "pct": 58.6,
          "rank": 1,
          "won": true
        },
        {
          "name": "김용호",
          "party": "민주공화당",
          "votes": 45877,
          "pct": 30.6,
          "rank": 2,
          "won": true
        }
      ]
    },
    {
      "sg_typecode": "2",
      "scope": "district",
      "sido": "강원특별자치도",
      "sigungu": "제3선거구(강릉시·명주군·삼척군)",
      "district": "제3선거구(강릉시·명주군·삼척군)",
      "candidates": [
        {
          "name": "김효영",
          "party": "민주공화당",
          "votes": 80377,
          "pct": 45.3,
          "rank": 1,
          "won": true
        },
        {
          "name": "김명윤",
          "party": "신민당",
          "votes": 42740,
          "pct": 24.1,
          "rank": 2,
          "won": true
        }
      ]
    },
    {
      "sg_typecode": "2",
      "scope": "district",
      "sido": "강원특별자치도",
      "sigungu": "제4선거구(속초시·인제군·고성군·양양군)",
      "district": "제4선거구(속초시·인제군·고성군·양양군)",
      "candidates": [
        {
          "name": "정일권",
          "party": "민주공화당",
          "votes": 57994,
          "pct": 64,
          "rank": 1,
          "won": true
        },
        {
          "name": "김인기",
          "party": "무소속",
          "votes": 18491,
          "pct": 20.4,
          "rank": 2,
          "won": true
        }
      ]
    },
    {
      "sg_typecode": "2",
      "scope": "district",
      "sido": "강원특별자치도",
      "sigungu": "제5선거구(영월군·평창군·정선군)",
      "district": "제5선거구(영월군·평창군·정선군)",
      "candidates": [
        {
          "name": "엄영달",
          "party": "신민당",
          "votes": 50199,
          "pct": 44.4,
          "rank": 1,
          "won": true
        },
        {
          "name": "장승태",
          "party": "민주공화당",
          "votes": 32751,
          "pct": 28.9,
          "rank": 2,
          "won": true
        }
      ]
    },
    {
      "sg_typecode": "2",
      "scope": "district",
      "sido": "경기도",
      "sigungu": "제1선거구(인천시동구·남구·북구·중구)",
      "district": "제1선거구(인천시동구·남구·북구·중구)",
      "candidates": [
        {
          "name": "김은하",
          "party": "신민당",
          "votes": 100694,
          "pct": 42.3,
          "rank": 1,
          "won": true
        },
        {
          "name": "유승원",
          "party": "민주공화당",
          "votes": 92543,
          "pct": 38.9,
          "rank": 2,
          "won": true
        }
      ]
    },
    {
      "sg_typecode": "2",
      "scope": "district",
      "sido": "경기도",
      "sigungu": "제2선거구(수원시·화성군)",
      "district": "제2선거구(수원시·화성군)",
      "candidates": [
        {
          "name": "이병희",
          "party": "민주공화당",
          "votes": 76748,
          "pct": 52.4,
          "rank": 1,
          "won": true
        },
        {
          "name": "김형일",
          "party": "신민당",
          "votes": 61150,
          "pct": 41.7,
          "rank": 2,
          "won": true
        }
      ]
    },
    {
      "sg_typecode": "2",
      "scope": "district",
      "sido": "경기도",
      "sigungu": "제3선거구(의정부시·양주군·파주군)",
      "district": "제3선거구(의정부시·양주군·파주군)",
      "candidates": [
        {
          "name": "박명근",
          "party": "민주공화당",
          "votes": 89465,
          "pct": 47.9,
          "rank": 1,
          "won": true
        },
        {
          "name": "이진용",
          "party": "무소속",
          "votes": 35768,
          "pct": 19.2,
          "rank": 2,
          "won": true
        }
      ]
    },
    {
      "sg_typecode": "2",
      "scope": "district",
      "sido": "경기도",
      "sigungu": "제4선거구(여주군·광주군·이천군)",
      "district": "제4선거구(여주군·광주군·이천군)",
      "candidates": [
        {
          "name": "차지철",
          "party": "민주공화당",
          "votes": 53586,
          "pct": 35.7,
          "rank": 1,
          "won": true
        },
        {
          "name": "오세응",
          "party": "신민당",
          "votes": 51399,
          "pct": 34.3,
          "rank": 2,
          "won": true
        }
      ]
    },
    {
      "sg_typecode": "2",
      "scope": "district",
      "sido": "경기도",
      "sigungu": "제5선거구(평택군·안성군·용인군)",
      "district": "제5선거구(평택군·안성군·용인군)",
      "candidates": [
        {
          "name": "유치송",
          "party": "신민당",
          "votes": 64895,
          "pct": 40.6,
          "rank": 1,
          "won": true
        },
        {
          "name": "서상린",
          "party": "민주공화당",
          "votes": 51134,
          "pct": 32,
          "rank": 2,
          "won": true
        }
      ]
    },
    {
      "sg_typecode": "2",
      "scope": "district",
      "sido": "경기도",
      "sigungu": "제6선거구(부천시·시흥군·옹진군)",
      "district": "제6선거구(부천시·시흥군·옹진군)",
      "candidates": [
        {
          "name": "이택돈",
          "party": "신민당",
          "votes": 49646,
          "pct": 38.1,
          "rank": 1,
          "won": true
        },
        {
          "name": "오학진",
          "party": "민주공화당",
          "votes": 49209,
          "pct": 37.7,
          "rank": 2,
          "won": true
        }
      ]
    },
    {
      "sg_typecode": "2",
      "scope": "district",
      "sido": "경기도",
      "sigungu": "제7선거구(김포군·고양군·강화군)",
      "district": "제7선거구(김포군·고양군·강화군)",
      "candidates": [
        {
          "name": "김재춘",
          "party": "민주공화당",
          "votes": 48532,
          "pct": 39.1,
          "rank": 1,
          "won": true
        },
        {
          "name": "김유탁",
          "party": "민주공화당",
          "votes": 31757,
          "pct": 25.6,
          "rank": 2,
          "won": true
        }
      ]
    },
    {
      "sg_typecode": "2",
      "scope": "district",
      "sido": "경기도",
      "sigungu": "제8선거구(연천군·포천군·가평군·양평군)",
      "district": "제8선거구(연천군·포천군·가평군·양평군)",
      "candidates": [
        {
          "name": "김용채",
          "party": "민주공화당",
          "votes": 0,
          "pct": null,
          "rank": 1,
          "won": true
        },
        {
          "name": "천명기",
          "party": "신민당",
          "votes": 0,
          "pct": null,
          "rank": 2,
          "won": true
        }
      ]
    },
    {
      "sg_typecode": "2",
      "scope": "district",
      "sido": "경상남도",
      "sigungu": "제1선거구(마산시·진해시·창원군)",
      "district": "제1선거구(마산시·진해시·창원군)",
      "candidates": [
        {
          "name": "이도환",
          "party": "민주공화당",
          "votes": 62150,
          "pct": 38.7,
          "rank": 1,
          "won": true
        },
        {
          "name": "황낙주",
          "party": "신민당",
          "votes": 59680,
          "pct": 37.2,
          "rank": 2,
          "won": true
        }
      ]
    },
    {
      "sg_typecode": "2",
      "scope": "district",
      "sido": "경상남도",
      "sigungu": "제2선거구(진주시·삼천포시·진양군·사천군)",
      "district": "제2선거구(진주시·삼천포시·진양군·사천군)",
      "candidates": [
        {
          "name": "최세흥",
          "party": "민주공화당",
          "votes": 39186,
          "pct": 27.8,
          "rank": 1,
          "won": true
        },
        {
          "name": "정헌주",
          "party": "신민당",
          "votes": 25219,
          "pct": 17.9,
          "rank": 2,
          "won": true
        }
      ]
    },
    {
      "sg_typecode": "2",
      "scope": "district",
      "sido": "경상남도",
      "sigungu": "제3선거구(충무시·통영군·거제군·고성군)",
      "district": "제3선거구(충무시·통영군·거제군·고성군)",
      "candidates": [
        {
          "name": "김주인",
          "party": "민주공화당",
          "votes": 53627,
          "pct": 37.8,
          "rank": 1,
          "won": true
        },
        {
          "name": "최재구",
          "party": "민주공화당",
          "votes": 48457,
          "pct": 34.2,
          "rank": 2,
          "won": true
        }
      ]
    },
    {
      "sg_typecode": "2",
      "scope": "district",
      "sido": "경상남도",
      "sigungu": "제4선거구(울산시·울주군·동래군)",
      "district": "제4선거구(울산시·울주군·동래군)",
      "candidates": [
        {
          "name": "김원규",
          "party": "민주공화당",
          "votes": 66652,
          "pct": 49.3,
          "rank": 1,
          "won": true
        },
        {
          "name": "최형우",
          "party": "신민당",
          "votes": 50395,
          "pct": 37.27,
          "rank": 2,
          "won": true
        }
      ]
    },
    {
      "sg_typecode": "2",
      "scope": "district",
      "sido": "경상남도",
      "sigungu": "제5선거구(의령군·함안군·합천군)",
      "district": "제5선거구(의령군·함안군·합천군)",
      "candidates": [
        {
          "name": "이상철",
          "party": "민주공화당",
          "votes": 0,
          "pct": null,
          "rank": 1,
          "won": true
        },
        {
          "name": "이상신",
          "party": "신민당",
          "votes": 0,
          "pct": null,
          "rank": 2,
          "won": true
        }
      ]
    },
    {
      "sg_typecode": "2",
      "scope": "district",
      "sido": "경상남도",
      "sigungu": "제6선거구(밀양군·창녕군)",
      "district": "제6선거구(밀양군·창녕군)",
      "candidates": [
        {
          "name": "박일",
          "party": "신민당",
          "votes": 46108,
          "pct": 38.2,
          "rank": 1,
          "won": true
        },
        {
          "name": "성낙현",
          "party": "민주공화당",
          "votes": 38243,
          "pct": 31.7,
          "rank": 2,
          "won": true
        }
      ]
    },
    {
      "sg_typecode": "2",
      "scope": "district",
      "sido": "경상남도",
      "sigungu": "제7선거구(김해군·양산군)",
      "district": "제7선거구(김해군·양산군)",
      "candidates": [
        {
          "name": "신상우",
          "party": "신민당",
          "votes": 34555,
          "pct": 38.2,
          "rank": 1,
          "won": true
        },
        {
          "name": "김영병",
          "party": "민주공화당",
          "votes": 34117,
          "pct": 37.8,
          "rank": 2,
          "won": true
        }
      ]
    },
    {
      "sg_typecode": "2",
      "scope": "district",
      "sido": "경상남도",
      "sigungu": "제8선거구(하동군·남해군)",
      "district": "제8선거구(하동군·남해군)",
      "candidates": [
        {
          "name": "신동관",
          "party": "민주공화당",
          "votes": 34747,
          "pct": 35.3,
          "rank": 1,
          "won": true
        },
        {
          "name": "문부식",
          "party": "신민당",
          "votes": 25588,
          "pct": 26,
          "rank": 2,
          "won": true
        }
      ]
    },
    {
      "sg_typecode": "2",
      "scope": "district",
      "sido": "경상남도",
      "sigungu": "제9선거구(거창군·함양군·산청군)",
      "district": "제9선거구(거창군·함양군·산청군)",
      "candidates": [
        {
          "name": "정우식",
          "party": "민주공화당",
          "votes": 42199,
          "pct": 33,
          "rank": 1,
          "won": true
        },
        {
          "name": "김동영",
          "party": "신민당",
          "votes": 28595,
          "pct": 22.3,
          "rank": 2,
          "won": true
        }
      ]
    },
    {
      "sg_typecode": "2",
      "scope": "district",
      "sido": "경상북도",
      "sigungu": "제10선거구(영주군·영양군·봉화군)",
      "district": "제10선거구(영주군·영양군·봉화군)",
      "candidates": [
        {
          "name": "박용만",
          "party": "신민당",
          "votes": 53041,
          "pct": 42.1,
          "rank": 1,
          "won": true
        },
        {
          "name": "권성기",
          "party": "민주공화당",
          "votes": 34281,
          "pct": 27.2,
          "rank": 2,
          "won": true
        }
      ]
    },
    {
      "sg_typecode": "2",
      "scope": "district",
      "sido": "경상북도",
      "sigungu": "제11선거구(문경군·예천군)",
      "district": "제11선거구(문경군·예천군)",
      "candidates": [
        {
          "name": "채문식",
          "party": "신민당",
          "votes": 49933,
          "pct": 47.1,
          "rank": 1,
          "won": true
        },
        {
          "name": "황재홍",
          "party": "민주공화당",
          "votes": 42543,
          "pct": 40.1,
          "rank": 2,
          "won": true
        }
      ]
    },
    {
      "sg_typecode": "2",
      "scope": "district",
      "sido": "경상북도",
      "sigungu": "제1선거구(대구시서구·북구·중구)",
      "district": "제1선거구(대구시서구·북구·중구)",
      "candidates": [
        {
          "name": "박찬",
          "party": "민주공화당",
          "votes": 68151,
          "pct": 39.37,
          "rank": 1,
          "won": true
        },
        {
          "name": "한병채",
          "party": "무소속",
          "votes": 41175,
          "pct": 23.79,
          "rank": 2,
          "won": true
        }
      ]
    },
    {
      "sg_typecode": "2",
      "scope": "district",
      "sido": "경상북도",
      "sigungu": "제2선거구(대구시남구·동구)",
      "district": "제2선거구(대구시남구·동구)",
      "candidates": [
        {
          "name": "이효상",
          "party": "민주공화당",
          "votes": 76245,
          "pct": 43.08,
          "rank": 1,
          "won": true
        },
        {
          "name": "신도환",
          "party": "신민당",
          "votes": 35105,
          "pct": 19.83,
          "rank": 2,
          "won": true
        }
      ]
    },
    {
      "sg_typecode": "2",
      "scope": "district",
      "sido": "경상북도",
      "sigungu": "제3선거구(포항시·울릉군·영일군·영천군)",
      "district": "제3선거구(포항시·울릉군·영일군·영천군)",
      "candidates": [
        {
          "name": "정무식",
          "party": "민주공화당",
          "votes": 65891,
          "pct": 35.4,
          "rank": 1,
          "won": true
        },
        {
          "name": "권오태",
          "party": "무소속",
          "votes": 55954,
          "pct": 30.1,
          "rank": 2,
          "won": true
        }
      ]
    },
    {
      "sg_typecode": "2",
      "scope": "district",
      "sido": "경상북도",
      "sigungu": "제4선거구(경주시·월성군·청도군)",
      "district": "제4선거구(경주시·월성군·청도군)",
      "candidates": [
        {
          "name": "박숙현",
          "party": "민주공화당",
          "votes": 56304,
          "pct": 35,
          "rank": 1,
          "won": true
        },
        {
          "name": "이영표",
          "party": "무소속",
          "votes": 20335,
          "pct": 12.7,
          "rank": 2,
          "won": true
        }
      ]
    },
    {
      "sg_typecode": "2",
      "scope": "district",
      "sido": "경상북도",
      "sigungu": "제5선거구(김천시·금릉군·상주군)",
      "district": "제5선거구(김천시·금릉군·상주군)",
      "candidates": [
        {
          "name": "김윤하",
          "party": "무소속",
          "votes": 46980,
          "pct": 28.6,
          "rank": 1,
          "won": true
        },
        {
          "name": "백남억",
          "party": "민주공화당",
          "votes": 41943,
          "pct": 25.5,
          "rank": 2,
          "won": true
        }
      ]
    },
    {
      "sg_typecode": "2",
      "scope": "district",
      "sido": "경상북도",
      "sigungu": "제6선거구(안동시·의성군·안동군)",
      "district": "제6선거구(안동시·의성군·안동군)",
      "candidates": [
        {
          "name": "김상년",
          "party": "민주공화당",
          "votes": 45868,
          "pct": 28.4,
          "rank": 1,
          "won": true
        },
        {
          "name": "박해충",
          "party": "신민당",
          "votes": 44914,
          "pct": 27.8,
          "rank": 2,
          "won": true
        }
      ]
    },
    {
      "sg_typecode": "2",
      "scope": "district",
      "sido": "경상북도",
      "sigungu": "제7선거구(달성군·경산군·고령군)",
      "district": "제7선거구(달성군·경산군·고령군)",
      "candidates": [
        {
          "name": "박준규",
          "party": "민주공화당",
          "votes": 34559,
          "pct": 25.2,
          "rank": 1,
          "won": true
        },
        {
          "name": "박주현",
          "party": "무소속",
          "votes": 29709,
          "pct": 21.7,
          "rank": 2,
          "won": true
        }
      ]
    },
    {
      "sg_typecode": "2",
      "scope": "district",
      "sido": "경상북도",
      "sigungu": "제8선거구(칠곡군·군위군·성주군·선산군)",
      "district": "제8선거구(칠곡군·군위군·성주군·선산군)",
      "candidates": [
        {
          "name": "신현확",
          "party": "민주공화당",
          "votes": 45330,
          "pct": 28.5,
          "rank": 1,
          "won": true
        },
        {
          "name": "김창환",
          "party": "신민당",
          "votes": 38013,
          "pct": 23.9,
          "rank": 2,
          "won": true
        }
      ]
    },
    {
      "sg_typecode": "2",
      "scope": "district",
      "sido": "경상북도",
      "sigungu": "제9선거구(영덕군·청송군·울진군)",
      "district": "제9선거구(영덕군·청송군·울진군)",
      "candidates": [
        {
          "name": "문태준",
          "party": "민주공화당",
          "votes": 35625,
          "pct": 33.2,
          "rank": 1,
          "won": true
        },
        {
          "name": "오준석",
          "party": "민주공화당",
          "votes": 28027,
          "pct": 26.1,
          "rank": 2,
          "won": true
        }
      ]
    },
    {
      "sg_typecode": "2",
      "scope": "district",
      "sido": "부산광역시",
      "sigungu": "제1선거구(중구·영도구)",
      "district": "제1선거구(중구·영도구)",
      "candidates": [
        {
          "name": "김상진",
          "party": "신민당",
          "votes": 44312,
          "pct": 41.8,
          "rank": 1,
          "won": true
        },
        {
          "name": "신기석",
          "party": "민주공화당",
          "votes": 27497,
          "pct": 26,
          "rank": 2,
          "won": true
        }
      ]
    },
    {
      "sg_typecode": "2",
      "scope": "district",
      "sido": "부산광역시",
      "sigungu": "제2선거구(서구·동구)",
      "district": "제2선거구(서구·동구)",
      "candidates": [
        {
          "name": "김영삼",
          "party": "신민당",
          "votes": 83661,
          "pct": 40.4,
          "rank": 1,
          "won": true
        },
        {
          "name": "박찬종",
          "party": "민주공화당",
          "votes": 72999,
          "pct": 35.2,
          "rank": 2,
          "won": true
        }
      ]
    },
    {
      "sg_typecode": "2",
      "scope": "district",
      "sido": "부산광역시",
      "sigungu": "제3선거구(부산진구갑·부산진구을)",
      "district": "제3선거구(부산진구갑·부산진구을)",
      "candidates": [
        {
          "name": "정해영",
          "party": "신민당",
          "votes": 87384,
          "pct": 38,
          "rank": 1,
          "won": true
        },
        {
          "name": "김임식",
          "party": "민주공화당",
          "votes": 82810,
          "pct": 36,
          "rank": 2,
          "won": true
        }
      ]
    },
    {
      "sg_typecode": "2",
      "scope": "district",
      "sido": "부산광역시",
      "sigungu": "제4선거구(동래구갑·동래구을)",
      "district": "제4선거구(동래구갑·동래구을)",
      "candidates": [
        {
          "name": "양찬우",
          "party": "민주공화당",
          "votes": 63081,
          "pct": 42.8,
          "rank": 1,
          "won": true
        },
        {
          "name": "이기택",
          "party": "신민당",
          "votes": 57757,
          "pct": 39.2,
          "rank": 2,
          "won": true
        }
      ]
    },
    {
      "sg_typecode": "2",
      "scope": "district",
      "sido": "서울특별시",
      "sigungu": "제1선거구(종로구·중구)",
      "district": "제1선거구(종로구·중구)",
      "candidates": [
        {
          "name": "장기영",
          "party": "민주공화당",
          "votes": 57607,
          "pct": 43.3,
          "rank": 1,
          "won": true
        },
        {
          "name": "정일형",
          "party": "신민당",
          "votes": 33183,
          "pct": 24.9,
          "rank": 2,
          "won": true
        }
      ]
    },
    {
      "sg_typecode": "2",
      "scope": "district",
      "sido": "서울특별시",
      "sigungu": "제2선거구(동대문구)",
      "district": "제2선거구(동대문구)",
      "candidates": [
        {
          "name": "강상욱",
          "party": "민주공화당",
          "votes": 140552,
          "pct": 51.9,
          "rank": 1,
          "won": true
        },
        {
          "name": "송원영",
          "party": "신민당",
          "votes": 76267,
          "pct": 28.2,
          "rank": 2,
          "won": true
        }
      ]
    },
    {
      "sg_typecode": "2",
      "scope": "district",
      "sido": "서울특별시",
      "sigungu": "제3선거구(성동구갑·성동구을)",
      "district": "제3선거구(성동구갑·성동구을)",
      "candidates": [
        {
          "name": "민병기",
          "party": "민주공화당",
          "votes": 87946,
          "pct": 32.9,
          "rank": 1,
          "won": true
        },
        {
          "name": "정운갑",
          "party": "신민당",
          "votes": 75090,
          "pct": 28.1,
          "rank": 2,
          "won": true
        }
      ]
    },
    {
      "sg_typecode": "2",
      "scope": "district",
      "sido": "서울특별시",
      "sigungu": "제4선거구(성북구갑·성북구을)",
      "district": "제4선거구(성북구갑·성북구을)",
      "candidates": [
        {
          "name": "고흥문",
          "party": "신민당",
          "votes": 100498,
          "pct": 32.2,
          "rank": 1,
          "won": true
        },
        {
          "name": "정래혁",
          "party": "민주공화당",
          "votes": 96186,
          "pct": 30.9,
          "rank": 2,
          "won": true
        }
      ]
    },
    {
      "sg_typecode": "2",
      "scope": "district",
      "sido": "서울특별시",
      "sigungu": "제5선거구(서대문구갑·서대문구을)",
      "district": "제5선거구(서대문구갑·서대문구을)",
      "candidates": [
        {
          "name": "김재광",
          "party": "무소속",
          "votes": 79480,
          "pct": 31.3,
          "rank": 1,
          "won": true
        },
        {
          "name": "오유방",
          "party": "민주공화당",
          "votes": 73677,
          "pct": 29,
          "rank": 2,
          "won": true
        }
      ]
    },
    {
      "sg_typecode": "2",
      "scope": "district",
      "sido": "서울특별시",
      "sigungu": "제6선거구(마포구·용산구)",
      "district": "제6선거구(마포구·용산구)",
      "candidates": [
        {
          "name": "김원만",
          "party": "신민당",
          "votes": 67140,
          "pct": 31.5,
          "rank": 1,
          "won": true
        },
        {
          "name": "노승환",
          "party": "신민당",
          "votes": 66031,
          "pct": 31,
          "rank": 2,
          "won": true
        }
      ]
    },
    {
      "sg_typecode": "2",
      "scope": "district",
      "sido": "서울특별시",
      "sigungu": "제7선거구(소할영등포구)",
      "district": "제7선거구(소할영등포구)",
      "candidates": [
        {
          "name": "김수한",
          "party": "신민당",
          "votes": 102875,
          "pct": 48.6,
          "rank": 1,
          "won": true
        },
        {
          "name": "정희섭",
          "party": "민주공화당",
          "votes": 53975,
          "pct": 25.5,
          "rank": 2,
          "won": true
        }
      ]
    },
    {
      "sg_typecode": "2",
      "scope": "district",
      "sido": "서울특별시",
      "sigungu": "제8선거구(영등포구일부)",
      "district": "제8선거구(영등포구일부)",
      "candidates": [
        {
          "name": "박한상",
          "party": "신민당",
          "votes": 77621,
          "pct": 37.9,
          "rank": 1,
          "won": true
        },
        {
          "name": "강병규",
          "party": "민주공화당",
          "votes": 71964,
          "pct": 35.1,
          "rank": 2,
          "won": true
        }
      ]
    },
    {
      "sg_typecode": "2",
      "scope": "district",
      "sido": "전라남도",
      "sigungu": "제10선거구(영광군·함평군·장성군)",
      "district": "제10선거구(영광군·함평군·장성군)",
      "candidates": [
        {
          "name": "윤인식",
          "party": "민주공화당",
          "votes": 45492,
          "pct": 34.1,
          "rank": 1,
          "won": true
        },
        {
          "name": "이진연",
          "party": "신민당",
          "votes": 32387,
          "pct": 24.3,
          "rank": 2,
          "won": true
        }
      ]
    },
    {
      "sg_typecode": "2",
      "scope": "district",
      "sido": "전라남도",
      "sigungu": "제1선거구(광주시)",
      "district": "제1선거구(광주시)",
      "candidates": [
        {
          "name": "김록영",
          "party": "민주통일당",
          "votes": 62072,
          "pct": 44.7,
          "rank": 1,
          "won": true
        },
        {
          "name": "박철",
          "party": "민주공화당",
          "votes": 38922,
          "pct": 28,
          "rank": 2,
          "won": true
        }
      ]
    },
    {
      "sg_typecode": "2",
      "scope": "district",
      "sido": "전라남도",
      "sigungu": "제2선거구(목포시·무안군·신안군)",
      "district": "제2선거구(목포시·무안군·신안군)",
      "candidates": [
        {
          "name": "강기천",
          "party": "민주공화당",
          "votes": 93213,
          "pct": 55.6,
          "rank": 1,
          "won": true
        },
        {
          "name": "김경인",
          "party": "민주통일당",
          "votes": 29279,
          "pct": 17.5,
          "rank": 2,
          "won": true
        }
      ]
    },
    {
      "sg_typecode": "2",
      "scope": "district",
      "sido": "전라남도",
      "sigungu": "제3선거구(여수시·광양군·여천군)",
      "district": "제3선거구(여수시·광양군·여천군)",
      "candidates": [
        {
          "name": "박병효",
          "party": "신민당",
          "votes": 43151,
          "pct": 33.3,
          "rank": 1,
          "won": true
        },
        {
          "name": "김상영",
          "party": "민주공화당",
          "votes": 39573,
          "pct": 30.6,
          "rank": 2,
          "won": true
        }
      ]
    },
    {
      "sg_typecode": "2",
      "scope": "district",
      "sido": "전라남도",
      "sigungu": "제4선거구(순천시·구례군·승주군)",
      "district": "제4선거구(순천시·구례군·승주군)",
      "candidates": [
        {
          "name": "박삼철",
          "party": "민주공화당",
          "votes": 46584,
          "pct": 40.1,
          "rank": 1,
          "won": true
        },
        {
          "name": "강길만",
          "party": "무소속",
          "votes": 23728,
          "pct": 20.4,
          "rank": 2,
          "won": true
        }
      ]
    },
    {
      "sg_typecode": "2",
      "scope": "district",
      "sido": "전라남도",
      "sigungu": "제5선거구(나주군·광산군)",
      "district": "제5선거구(나주군·광산군)",
      "candidates": [
        {
          "name": "임인채",
          "party": "민주공화당",
          "votes": 39926,
          "pct": 34.5,
          "rank": 1,
          "won": true
        },
        {
          "name": "김윤덕",
          "party": "신민당",
          "votes": 35655,
          "pct": 30.8,
          "rank": 2,
          "won": true
        }
      ]
    },
    {
      "sg_typecode": "2",
      "scope": "district",
      "sido": "전라남도",
      "sigungu": "제6선거구(담양군·곡성군·화순군)",
      "district": "제6선거구(담양군·곡성군·화순군)",
      "candidates": [
        {
          "name": "문형태",
          "party": "민주공화당",
          "votes": 79067,
          "pct": 59.1,
          "rank": 1,
          "won": true
        },
        {
          "name": "고재청",
          "party": "신민당",
          "votes": 30751,
          "pct": 23,
          "rank": 2,
          "won": true
        }
      ]
    },
    {
      "sg_typecode": "2",
      "scope": "district",
      "sido": "전라남도",
      "sigungu": "제7선거구(보성군·고흥군)",
      "district": "제7선거구(보성군·고흥군)",
      "candidates": [
        {
          "name": "신형식",
          "party": "민주공화당",
          "votes": 69903,
          "pct": 47.8,
          "rank": 1,
          "won": true
        },
        {
          "name": "이중재",
          "party": "신민당",
          "votes": 45986,
          "pct": 31.4,
          "rank": 2,
          "won": true
        }
      ]
    },
    {
      "sg_typecode": "2",
      "scope": "district",
      "sido": "전라남도",
      "sigungu": "제8선거구(장흥군·강진군·영암군·완도군)",
      "district": "제8선거구(장흥군·강진군·영암군·완도군)",
      "candidates": [
        {
          "name": "길전식",
          "party": "민주공화당",
          "votes": 89035,
          "pct": 43.8,
          "rank": 1,
          "won": true
        },
        {
          "name": "황호동",
          "party": "신민당",
          "votes": 58218,
          "pct": 28.6,
          "rank": 2,
          "won": true
        }
      ]
    },
    {
      "sg_typecode": "2",
      "scope": "district",
      "sido": "전라남도",
      "sigungu": "제9선거구(해남군·진도군)",
      "district": "제9선거구(해남군·진도군)",
      "candidates": [
        {
          "name": "임충식",
          "party": "민주공화당",
          "votes": 64466,
          "pct": 56.5,
          "rank": 1,
          "won": true
        },
        {
          "name": "박귀수",
          "party": "무소속",
          "votes": 22242,
          "pct": 19.5,
          "rank": 2,
          "won": true
        }
      ]
    },
    {
      "sg_typecode": "2",
      "scope": "district",
      "sido": "전북특별자치도",
      "sigungu": "제1선거구(전주시·완주군)",
      "district": "제1선거구(전주시·완주군)",
      "candidates": [
        {
          "name": "이철승",
          "party": "신민당",
          "votes": 73803,
          "pct": 49.6,
          "rank": 1,
          "won": true
        },
        {
          "name": "유기정",
          "party": "민주공화당",
          "votes": 41726,
          "pct": 28,
          "rank": 2,
          "won": true
        }
      ]
    },
    {
      "sg_typecode": "2",
      "scope": "district",
      "sido": "전북특별자치도",
      "sigungu": "제2선거구(군산시·이리시·옥구군·익산군)",
      "district": "제2선거구(군산시·이리시·옥구군·익산군)",
      "candidates": [
        {
          "name": "채영철",
          "party": "민주공화당",
          "votes": 77140,
          "pct": 41.7,
          "rank": 1,
          "won": true
        },
        {
          "name": "김현기",
          "party": "신민당",
          "votes": 53972,
          "pct": 29.2,
          "rank": 2,
          "won": true
        }
      ]
    },
    {
      "sg_typecode": "2",
      "scope": "district",
      "sido": "전북특별자치도",
      "sigungu": "제3선거구(진안군·무주군·장수군)",
      "district": "제3선거구(진안군·무주군·장수군)",
      "candidates": [
        {
          "name": "최성석",
          "party": "신민당",
          "votes": 29654,
          "pct": 32.2,
          "rank": 1,
          "won": true
        },
        {
          "name": "김광수",
          "party": "무소속",
          "votes": 24891,
          "pct": 27,
          "rank": 2,
          "won": true
        }
      ]
    },
    {
      "sg_typecode": "2",
      "scope": "district",
      "sido": "전북특별자치도",
      "sigungu": "제4선거구(남원군·임실군·순창군)",
      "district": "제4선거구(남원군·임실군·순창군)",
      "candidates": [
        {
          "name": "손주항",
          "party": "무소속",
          "votes": 51592,
          "pct": 36.5,
          "rank": 1,
          "won": true
        },
        {
          "name": "양해준",
          "party": "신민당",
          "votes": 42811,
          "pct": 30.3,
          "rank": 2,
          "won": true
        }
      ]
    },
    {
      "sg_typecode": "2",
      "scope": "district",
      "sido": "전북특별자치도",
      "sigungu": "제5선거구(정읍군·김제군)",
      "district": "제5선거구(정읍군·김제군)",
      "candidates": [
        {
          "name": "김택하",
          "party": "무소속",
          "votes": 44319,
          "pct": 26.6,
          "rank": 1,
          "won": true
        },
        {
          "name": "장경순",
          "party": "민주공화당",
          "votes": 38096,
          "pct": 22.8,
          "rank": 2,
          "won": true
        }
      ]
    },
    {
      "sg_typecode": "2",
      "scope": "district",
      "sido": "전북특별자치도",
      "sigungu": "제6선거구(고창군·부안군)",
      "district": "제6선거구(고창군·부안군)",
      "candidates": [
        {
          "name": "이병옥",
          "party": "민주공화당",
          "votes": 39684,
          "pct": 34,
          "rank": 1,
          "won": true
        },
        {
          "name": "진의종",
          "party": "무소속",
          "votes": 28545,
          "pct": 24.5,
          "rank": 2,
          "won": true
        }
      ]
    },
    {
      "sg_typecode": "2",
      "scope": "district",
      "sido": "제주특별자치도",
      "sigungu": "제주도선거구(제주시·북제주군·남제주군)",
      "district": "제주도선거구(제주시·북제주군·남제주군)",
      "candidates": [
        {
          "name": "홍병철",
          "party": "민주공화당",
          "votes": 49326,
          "pct": 35.8,
          "rank": 1,
          "won": true
        },
        {
          "name": "양정규",
          "party": "무소속",
          "votes": 23989,
          "pct": 17.4,
          "rank": 2,
          "won": true
        }
      ]
    },
    {
      "sg_typecode": "2",
      "scope": "district",
      "sido": "충청남도",
      "sigungu": "제1선거구(대전시갑·대전시을)",
      "district": "제1선거구(대전시갑·대전시을)",
      "candidates": [
        {
          "name": "김용태",
          "party": "민주공화당",
          "votes": 54208,
          "pct": 37.6,
          "rank": 1,
          "won": true
        },
        {
          "name": "임호",
          "party": "무소속",
          "votes": 38572,
          "pct": 26.7,
          "rank": 2,
          "won": true
        }
      ]
    },
    {
      "sg_typecode": "2",
      "scope": "district",
      "sido": "충청남도",
      "sigungu": "제2선거구(천안시·아산군·천원군)",
      "district": "제2선거구(천안시·아산군·천원군)",
      "candidates": [
        {
          "name": "김종철",
          "party": "민주공화당",
          "votes": 61718,
          "pct": 43.2,
          "rank": 1,
          "won": true
        },
        {
          "name": "황명수",
          "party": "신민당",
          "votes": 50967,
          "pct": 35.6,
          "rank": 2,
          "won": true
        }
      ]
    },
    {
      "sg_typecode": "2",
      "scope": "district",
      "sido": "충청남도",
      "sigungu": "제3선거구(대덕군·연기군·금산군)",
      "district": "제3선거구(대덕군·연기군·금산군)",
      "candidates": [
        {
          "name": "류진산",
          "party": "신민당",
          "votes": 54670,
          "pct": 43.4,
          "rank": 1,
          "won": true
        },
        {
          "name": "김제원",
          "party": "민주공화당",
          "votes": 44123,
          "pct": 35.1,
          "rank": 2,
          "won": true
        }
      ]
    },
    {
      "sg_typecode": "2",
      "scope": "district",
      "sido": "충청남도",
      "sigungu": "제4선거구(논산군·공주군)",
      "district": "제4선거구(논산군·공주군)",
      "candidates": [
        {
          "name": "박찬",
          "party": "신민당",
          "votes": 43857,
          "pct": 30.9,
          "rank": 1,
          "won": true
        },
        {
          "name": "이병주",
          "party": "민주공화당",
          "votes": 42088,
          "pct": 29.6,
          "rank": 2,
          "won": true
        }
      ]
    },
    {
      "sg_typecode": "2",
      "scope": "district",
      "sido": "충청남도",
      "sigungu": "제5선거구(부여군·서천군·보령군)",
      "district": "제5선거구(부여군·서천군·보령군)",
      "candidates": [
        {
          "name": "김옥선",
          "party": "신민당",
          "votes": 70644,
          "pct": 41.1,
          "rank": 1,
          "won": true
        },
        {
          "name": "김종익",
          "party": "민주공화당",
          "votes": 67248,
          "pct": 39.1,
          "rank": 2,
          "won": true
        }
      ]
    },
    {
      "sg_typecode": "2",
      "scope": "district",
      "sido": "충청남도",
      "sigungu": "제6선거구(홍성군·청양군·예산군)",
      "district": "제6선거구(홍성군·청양군·예산군)",
      "candidates": [
        {
          "name": "장영순",
          "party": "민주공화당",
          "votes": 60112,
          "pct": 41.8,
          "rank": 1,
          "won": true
        },
        {
          "name": "한건수",
          "party": "신민당",
          "votes": 58651,
          "pct": 40.8,
          "rank": 2,
          "won": true
        }
      ]
    },
    {
      "sg_typecode": "2",
      "scope": "district",
      "sido": "충청남도",
      "sigungu": "제7선거구(서산군·당진군)",
      "district": "제7선거구(서산군·당진군)",
      "candidates": [
        {
          "name": "한영수",
          "party": "무소속",
          "votes": 51527,
          "pct": 33.1,
          "rank": 1,
          "won": true
        },
        {
          "name": "유제연",
          "party": "신민당",
          "votes": 35171,
          "pct": 22.6,
          "rank": 2,
          "won": true
        }
      ]
    },
    {
      "sg_typecode": "2",
      "scope": "district",
      "sido": "충청북도",
      "sigungu": "제1선거구(청주시·청원군)",
      "district": "제1선거구(청주시·청원군)",
      "candidates": [
        {
          "name": "민기식",
          "party": "민주공화당",
          "votes": 50521,
          "pct": 39,
          "rank": 1,
          "won": true
        },
        {
          "name": "이민우",
          "party": "신민당",
          "votes": 33699,
          "pct": 26,
          "rank": 2,
          "won": true
        }
      ]
    },
    {
      "sg_typecode": "2",
      "scope": "district",
      "sido": "충청북도",
      "sigungu": "제2선거구(충주시·중원군·제천군·단양군)",
      "district": "제2선거구(충주시·중원군·제천군·단양군)",
      "candidates": [
        {
          "name": "이종근",
          "party": "민주공화당",
          "votes": 73320,
          "pct": 43,
          "rank": 1,
          "won": true
        },
        {
          "name": "이해원",
          "party": "민주공화당",
          "votes": 38001,
          "pct": 22.3,
          "rank": 2,
          "won": true
        }
      ]
    },
    {
      "sg_typecode": "2",
      "scope": "district",
      "sido": "충청북도",
      "sigungu": "제3선거구(보은군·옥천군·영동군)",
      "district": "제3선거구(보은군·옥천군·영동군)",
      "candidates": [
        {
          "name": "육인수",
          "party": "민주공화당",
          "votes": 44845,
          "pct": 35.6,
          "rank": 1,
          "won": true
        },
        {
          "name": "이용희",
          "party": "무소속",
          "votes": 23483,
          "pct": 18.7,
          "rank": 2,
          "won": true
        }
      ]
    },
    {
      "sg_typecode": "2",
      "scope": "district",
      "sido": "충청북도",
      "sigungu": "제4선거구(진천군·괴산군·음성군)",
      "district": "제4선거구(진천군·괴산군·음성군)",
      "candidates": [
        {
          "name": "이충환",
          "party": "신민당",
          "votes": 47760,
          "pct": 39.4,
          "rank": 1,
          "won": true
        },
        {
          "name": "김원태",
          "party": "민주공화당",
          "votes": 40932,
          "pct": 33.8,
          "rank": 2,
          "won": true
        }
      ]
    },
    {
      "sg_typecode": "7",
      "scope": "nation",
      "sido": "전국",
      "sigungu": "전국",
      "candidates": [
        {
          "name": "유신정우회",
          "party": "유신정우회",
          "proportional_seats": 73
        }
      ]
    }
  ]
}
